{
    "_id": "Xdmz09kzLjIxWz9C",
    "img": "systems/xprpg/icons/features/feats/feats.webp",
    "name": "Tactical Debilitations",
    "system": {
        "actionType": {
            "value": "passive"
        },
        "actions": {
            "value": null
        },
        "description": {
            "value": "<p>You learn new debilitations that grant you tactical advantages against your foes. Add the following debilitations to the list you can choose from when you use @UUID[Compendium.xprpg.actionsxprpg.Debilitating Strike]{Debilitating Strike}.</p>\n<ul>\n<li><strong>Debilitation</strong> The target can't use reactions.</li>\n<li><strong>Debilitation</strong> The target can't flank or contribute to allies' flanking.</li>\n</ul>"
        },
        "featType": {
            "value": "class"
        },
        "level": {
            "value": 10
        },
        "prerequisites": {
            "value": [
                {
                    "value": "scoundrel racket"
                },
                {
                    "value": "Debilitating Strike"
                }
            ]
        },
        "rules": [
            {
                "key": "Note",
                "predicate": [
                    "target:condition:flat-footed"
                ],
                "selector": "strike-damage",
                "text": "<span class='xprpg-icon'>f</span> @UUID[Compendium.xprpg.feats-srd.Tactical Debilitations]{Tactical Debilitations}"
            }
        ],
        "source": {
            "value": "Xenos Paragon Core Rulebook"
        },
        "traits": {
            "rarity": "common",
            "value": [
                "rogue"
            ]
        }
    },
    "type": "feat"
}
