{
    "_id": "RbslST0RZPXj6Eby",
    "img": "systems/xprpg/icons/default-icons/deity.svg",
    "name": "Ashukharma",
    "system": {
        "ability": [
            "con",
            "int"
        ],
        "alignment": {
            "follower": [
                "CG",
                "N",
                "CN"
            ],
            "own": "CN"
        },
        "category": "deity",
        "description": {
            "value": "<p>Ashukharma is the Vudran goddess of canyons and cliffs. She is the jilted lover of Dinehdal, god of mountain peaks, and lover of Matravash, goddess of the Matra River; her tale draws prayers from scorned lovers and those dealing with rifts between themselves and their friends or families.</p>\n<p><strong>Edicts</strong> Hinder travel, create and enforce physical and emotional boundaries, build defensive earthworks</p>\n<p><strong>Anathema</strong> Destroy a natural barrier, pursue a personal relationship after being refused, betray a lover</p>"
        },
        "domains": {
            "alternate": [],
            "primary": [
                "earth",
                "might",
                "protection",
                "repose"
            ]
        },
        "font": [
            "harm",
            "heal"
        ],
        "rules": [],
        "skill": "cra",
        "source": {
            "value": "Xenos Paragon Core Rulebook"
        },
        "spells": {
            "1": "Compendium.xprpg.spells-srd.0uRpypf1Hi7ahvTl",
            "4": "Compendium.xprpg.spells-srd.McnPlLFvKtQVXNcG",
            "5": "Compendium.xprpg.spells-srd.kOa055FIrO9Smnya"
        },
        "weapons": [
            "greatsword"
        ]
    },
    "type": "deity"
}
